scripts/__init__.py
scripts/compute_mi.py
scripts/config/__init__.py
scripts/config/config.yaml
scripts/config/data/csv.yaml
scripts/config/data/multimixture.yaml
scripts/config/experiment/eval_distribution_mi.yaml
scripts/config/logger/pandas.yaml
scripts/config/logger/wandb.yaml
scripts/config/mi_estimator/alpha_tuba.yaml
scripts/config/mi_estimator/binned.yaml
scripts/config/mi_estimator/club.yaml
scripts/config/mi_estimator/doe.yaml
scripts/config/mi_estimator/dummy_discriminative.yaml
scripts/config/mi_estimator/dummy_generative.yaml
scripts/config/mi_estimator/flo.yaml
scripts/config/mi_estimator/gm.yaml
scripts/config/mi_estimator/hybrid_pq.yaml
scripts/config/mi_estimator/hybrid_resampled.yaml
scripts/config/mi_estimator/hybrid_reweighed.yaml
scripts/config/mi_estimator/infonce.yaml
scripts/config/mi_estimator/js.yaml
scripts/config/mi_estimator/l1out.yaml
scripts/config/mi_estimator/mine.yaml
scripts/config/mi_estimator/nwj.yaml
scripts/config/mi_estimator/pq.yaml
scripts/config/mi_estimator/smile.yaml
scripts/config/mi_estimator/tuba.yaml
scripts/config/quantization/kmeans.yaml
scripts/config/quantization/vqvae.yaml
torch_mist/__init__.py
torch_mist/baseline/__init__.py
torch_mist/baseline/base.py
torch_mist/baseline/factories.py
torch_mist/critic/__init__.py
torch_mist/critic/base.py
torch_mist/critic/constant.py
torch_mist/critic/factories.py
torch_mist/critic/joint.py
torch_mist/critic/separable.py
torch_mist/data/__init__.py
torch_mist/data/multimixture.py
torch_mist/data/multivariate.py
torch_mist/data/utils.py
torch_mist/decomposition/__init__.py
torch_mist/decomposition/base.py
torch_mist/decomposition/ceb.py
torch_mist/decomposition/mib.py
torch_mist/decomposition/mid.py
torch_mist/decomposition/tib.py
torch_mist/decomposition/tinfomax.py
torch_mist/decomposition/vib.py
torch_mist/distributions/__init__.py
torch_mist/distributions/caching.py
torch_mist/distributions/categorical.py
torch_mist/distributions/conditional/__init__.py
torch_mist-0.2.17.dist-info/LICENSE
torch_mist-0.2.17.dist-info/METADATA
torch_mist-0.2.17.dist-info/WHEEL
torch_mist-0.2.17.dist-info/entry_points.txt
torch_mist-0.2.17.dist-info/RECORD
