Metadata-Version: 2.1
Name: torch-mist
Version: 0.2.17
Summary: Mutual Information Estimation toolkit based on pytorch
License: MIT
Author: Marco Federici
Requires-Python: >=3.8,<4.0
Classifier: License :: OSI Approved :: MIT License
Classifier: Programming Language :: Python :: 3
Classifier: Programming Language :: Python :: 3.8
Classifier: Programming Language :: Python :: 3.9
Classifier: Programming Language :: Python :: 3.10
Classifier: Programming Language :: Python :: 3.11
Requires-Dist: hydra-core (>=1.3.2,<2.0.0)
Requires-Dist: mpld3 (>=0.5.10,<0.6.0)
Requires-Dist: numpy (>=1.20.0,<2.0.0)
Requires-Dist: pyro-ppl (>=1.8.5,<2.0.0)
Requires-Dist: scikit-learn (>=1.3.0,<2.0.0)
Requires-Dist: torch (>=2.0.0,<3.0.0)
